dash_flow_example/__init__.py
dash_flow_example/bundle.js
dash_flow_example/metadata.json
dash_flow_example/version.py
dash_flow_example-0.0.5.dist-info/METADATA
dash_flow_example-0.0.5.dist-info/RECORD
dash_flow_example-0.0.5.dist-info/WHEEL
dash_flow_example-0.0.5.dist-info/top_level.txt
