Metadata-Version: 2.1
Name: dash-flow-example
Version: 0.0.5
Summary: Example of a Dash library that uses Flow Types
Home-page: UNKNOWN
Author: plotly
Author-email: UNKNOWN
License: MIT
Platform: UNKNOWN
